bbq_map_demo/__init__.py
bbq_map_demo-0.1.0.dist-info/METADATA
bbq_map_demo-0.1.0.dist-info/WHEEL
bbq_map_demo-0.1.0.dist-info/entry_points.txt
bbq_map_demo-0.1.0.dist-info/RECORD
