Metadata-Version: 2.4
Name: bbq-map-demo
Version: 0.1.0
Summary: Add your description here
Author-email: "tony.dai" <893349926@qq.com>
Requires-Python: >=3.13
Requires-Dist: mcp[cli]>=1.10.1
